bchlibcaronoff.cpython-39-darwin.so
bchlibcaronoff-1.0.4.dist-info/COPYING
bchlibcaronoff-1.0.4.dist-info/METADATA
bchlibcaronoff-1.0.4.dist-info/WHEEL
bchlibcaronoff-1.0.4.dist-info/top_level.txt
bchlibcaronoff-1.0.4.dist-info/RECORD
