Metadata-Version: 2.1
Name: bchlibcaronoff
Version: 1.0.4
Summary: A python wrapper module for the kernel BCH library.
Home-page: https://github.com/jkent/python-bchlib
Author: Jeff Kent
Author-email: jeff@jkent.net
Maintainer: Jeff Kent
Maintainer-email: jeff@jkent.net
License: GNU GPLv2
Platform: UNKNOWN
Classifier: Development Status :: 4 - Beta
Classifier: Intended Audience :: Developers
Classifier: License :: OSI Approved :: GNU General Public License v2 (GPLv2)
Classifier: Operating System :: POSIX :: Linux
Classifier: Programming Language :: C
Classifier: Programming Language :: Python :: 3
Classifier: Topic :: Security :: Cryptography
Classifier: Topic :: Software Development :: Libraries :: Python Modules
License-File: COPYING
